MANIFEST.in
README
setup.py
django_actions/__init__.py
django_actions/lib.py
django_actions/models.py
django_actions/urls.py
django_actions/views.py
django_actions.egg-info/PKG-INFO
django_actions.egg-info/SOURCES.txt
django_actions.egg-info/dependency_links.txt
django_actions.egg-info/top_level.txt
django_actions/templates/__init__.py
django_actions/templates/django_actions/__init__.py
django_actions/templates/django_actions/index.html