Metadata-Version: 1.0
Name: django-actions
Version: 0.0.5
Summary: UNKNOWN
Home-page: UNKNOWN
Author: Kashif Malik
Author-email: kashif610@gmail.com
License: UNKNOWN
Platform: UNKNOWN
